optional/__init__.py
optional/abstract_optional.py
optional/compatible_abc.py
optional/exceptions.py
optional/nothing.py
optional/optional.py
optional/something.py
optional.py-1.3.1.dist-info/LICENSE
optional.py-1.3.1.dist-info/WHEEL
optional.py-1.3.1.dist-info/METADATA
optional.py-1.3.1.dist-info/RECORD
